{
  "generated": "2026-05-14T12:58:22.631622+00:00",
  "news_count": 0,
  "dvids_count": 3,
  "news": [],
  "dvids": [
    {
      "id": "news:565238",
      "title": "U.S., Cameroon Boost Maritime Security with Unmanned Systems During Obangame Express 2026",
      "desc": "U.S. Sixth Fleet successfully integrated advanced unmanned surface vessels (USVs) during Exercise Obangame Express 2026 in Douala, Cameroon.",
      "type": "news",
      "branch": "Navy",
      "unit_name": "U.S. Naval Forces Europe-Africa/U.S. Sixth Fleet",
      "timestamp": "2026-05-14T06:27:10+00:00",
      "url": "https://www.dvidshub.net/news/565238/us-cameroon-boost-maritime-security-with-unmanned-systems-during-obangame-express-2026",
      "thumbnail_url": "",
      "commands": [
        "EUCOM"
      ],
      "location_display": ""
    },
    {
      "id": "news:565162",
      "title": "Carrier Air Wing 8 Returns from Historic 11-Month Deployment",
      "desc": "Aircraft of the Gerald R. Ford Carrier Strike Group’s Carrier Air Wing (CVW) 8 returned to their home naval air stations May 11, following an historic and successful 11-month deployment to the U.S. Central Command, U.S. European Command and U.S. Southern Command areas of operations.",
      "type": "news",
      "branch": "Navy",
      "unit_name": "Commander, Naval Air Force Atlantic",
      "timestamp": "2026-05-13T15:40:59+00:00",
      "url": "https://www.dvidshub.net/news/565162/carrier-air-wing-8-returns-historic-11-month-deployment",
      "thumbnail_url": "",
      "commands": [
        "CENTCOM",
        "EUCOM"
      ],
      "location_display": ""
    },
    {
      "id": "video:1006671",
      "title": "U.S. Blockade Against Iran - One Month",
      "desc": "Four weeks ago, CENTCOM began implementing the blockade against ships entering and exiting Iran’s ports. As of May 13, American forces have redirected 67 commercial vessels, allowed 15 supporting humanitarian aid to pass, and disabled 4 to ensure compliance. (U.S. Central Command Video)",
      "type": "video",
      "branch": "Joint",
      "unit_name": "U.S. Central Command Public Affairs",
      "timestamp": "2026-05-13T15:27:52+00:00",
      "url": "https://www.dvidshub.net/video/1006671/us-blockade-against-iran-one-month",
      "thumbnail_url": "",
      "commands": [
        "CENTCOM"
      ],
      "location_display": ""
    }
  ]
}